magic/__init__.py
magic/algorithms.py
magic/cli.py
magicdsa-0.1.2.dist-info/licenses/LICENSE.txt
magicdsa-0.1.2.dist-info/METADATA
magicdsa-0.1.2.dist-info/WHEEL
magicdsa-0.1.2.dist-info/top_level.txt
magicdsa-0.1.2.dist-info/RECORD
