Metadata-Version: 2.4
Name: magicdsa
Version: 0.1.2
Summary: A powerful Python package to explore and learn 300+ algorithms with a single function call.
Author-email: Shivendra Singh <2k22.csai2211760@gmail.com>
License: MIT
Project-URL: Homepage, https://github.com/shivendrasingh11249/magic-algos
Project-URL: Source, https://github.com/shivendrasingh11249/magic-algos
Project-URL: Documentation, https://pypi.org/project/magic-algos/
Keywords: algorithms,data-structures,DSA,learning,python,magic,interview-prep
Classifier: Development Status :: 4 - Beta
Classifier: Intended Audience :: Developers
Classifier: Programming Language :: Python :: 3
Classifier: License :: OSI Approved :: MIT License
Classifier: Operating System :: OS Independent
Classifier: Topic :: Education
Classifier: Topic :: Software Development :: Libraries :: Python Modules
Requires-Python: >=3.8
License-File: LICENSE.txt
Dynamic: license-file
